[{"`node_id`": 1, "`code`": 720, "`test`": "N\u00e1stroje", "`query`": "tools", "`folder`": "", "`header`": ""}, {"`node_id`": 2, "`code`": 740, "`test`": "Data", "`query`": "", "`folder`": "SOWE", "`header`": ""}, {"`node_id`": 3, "`code`": 710, "`test`": "Materi\u00e1ly", "`query`": "", "`folder`": "MAT", "`header`": ""}, {"`node_id`": 4, "`code`": 730, "`test`": "Energie", "`query`": "", "`folder`": "", "`header`": ""}, {"`node_id`": 5, "`code`": 741, "`test`": "OS", "`query`": "", "`folder`": "OSC", "`header`": ""}, {"`node_id`": 6, "`code`": 743, "`test`": "Software", "`query`": "", "`folder`": "SFW", "`header`": ""}, {"`node_id`": 7, "`code`": 744, "`test`": "Programming", "`query`": "", "`folder`": "PRG", "`header`": ""}, {"`node_id`": 8, "`code`": 745, "`test`": "Networking", "`query`": "", "`folder`": "NET", "`header`": ""}, {"`node_id`": 9, "`code`": 752, "`test`": "Domy", "`query`": "", "`folder`": "", "`header`": ""}, {"`node_id`": 10, "`code`": 753, "`test`": "Infrastruktura", "`query`": "", "`folder`": "", "`header`": ""}, {"`node_id`": 11, "`code`": 554, "`test`": "Astrologie", "`query`": "", "`folder`": "ASG", "`header`": ""}, {"`node_id`": 12, "`code`": 423, "`test`": "Protista - Jednobun\u011b\u010dn\u00ed", "`query`": null, "`folder`": "PRO", "`header`": null}, {"`node_id`": 13, "`code`": 424, "`test`": "Fungi - Houby", "`query`": "funga", "`folder`": "FUN", "`header`": ""}, {"`node_id`": 14, "`code`": 425, "`test`": "Plantae - Rostliny", "`query`": "flora", "`folder`": "ROS", "`header`": ""}, {"`node_id`": 15, "`code`": 426, "`test`": "Animalia -\u017divo\u010dichov\u00e9", "`query`": "anima", "`folder`": "ANI", "`header`": ""}, {"`node_id`": 24, "`code`": 711, "`test`": "P\u0159\u00edrodn\u00ed", "`query`": "", "`folder`": "", "`header`": ""}, {"`node_id`": 29, "`code`": 712, "`test`": "Um\u011bl\u00e9", "`query`": "", "`folder`": "", "`header`": ""}, {"`node_id`": 30, "`code`": 660, "`test`": "Kvatov\u00e1 teorie", "`query`": "", "`folder`": "KVA", "`header`": ""}, {"`node_id`": 31, "`code`": 650, "`test`": "Filozofie", "`query`": "", "`folder`": "FIL", "`header`": ""}, {"`node_id`": 32, "`code`": 640, "`test`": "Astronomie", "`query`": "", "`folder`": "AST", "`header`": ""}, {"`node_id`": 33, "`code`": 420, "`test`": "\u017divot a Biologie", "`query`": "", "`folder`": "BIOLOG", "`header`": ""}, {"`node_id`": 34, "`code`": 523, "`test`": "Chov a P\u011bstov\u00e1n\u00ed", "`query`": "", "`folder`": "FAR", "`header`": ""}, {"`node_id`": 37, "`code`": 433, "`test`": "Ekologie", "`query`": "", "`folder`": "EKO", "`header`": ""}, {"`node_id`": 38, "`code`": 713, "`test`": "Toxikologie", "`query`": "", "`folder`": "", "`header`": ""}, {"`node_id`": 39, "`code`": 432, "`test`": "Geologie", "`query`": "", "`folder`": "GEL", "`header`": ""}, {"`node_id`": 40, "`code`": 511, "`test`": "Aura", "`query`": "", "`folder`": "AUR", "`header`": ""}, {"`node_id`": 41, "`code`": 510, "`test`": "J\u00eddlo a Zdraven\u00ed", "`query`": "", "`folder`": "MHEAL", "`header`": ""}, {"`node_id`": 42, "`code`": 522, "`test`": "Venku", "`query`": "", "`folder`": "OUT", "`header`": ""}, {"`node_id`": 43, "`code`": 520, "`test`": "Pohyb", "`query`": "", "`folder`": "MOVEM", "`header`": ""}, {"`node_id`": 44, "`code`": 513, "`test`": "Recepty P\u0159\u00edpravy", "`query`": "recepty", "`folder`": "REC", "`header`": ""}, {"`node_id`": 45, "`code`": 530, "`test`": "Kultura", "`query`": "", "`folder`": "CULTUR", "`header`": ""}, {"`node_id`": 46, "`code`": 540, "`test`": "Z\u00e1kony", "`query`": "", "`folder`": "", "`header`": ""}, {"`node_id`": 47, "`code`": 550, "`test`": "Magie", "`query`": "", "`folder`": "MAG", "`header`": ""}, {"`node_id`": 48, "`code`": 610, "`test`": "Matematika", "`query`": "", "`folder`": "MAT", "`header`": ""}, {"`node_id`": 49, "`code`": 620, "`test`": "Fyzika", "`query`": "jednotky", "`folder`": "FYZ", "`header`": ""}, {"`node_id`": 50, "`code`": 630, "`test`": "Chemie", "`query`": "", "`folder`": "CHEMY", "`header`": ""}, {"`node_id`": 51, "`code`": 633, "`test`": "Organick\u00e1 chemie", "`query`": "", "`folder`": "OCH", "`header`": ""}, {"`node_id`": 52, "`code`": 634, "`test`": "Biochemie", "`query`": "", "`folder`": "BCH", "`header`": ""}, {"`node_id`": 53, "`code`": 422, "`test`": "Procaryotae - Bacterium", "`query`": "bakteria", "`folder`": "BAC", "`header`": ""}, {"`node_id`": 115, "`code`": 521, "`test`": "Hry", "`query`": "hrani", "`folder`": "HRA", "`header`": ""}, {"`node_id`": 120, "`code`": 724, "`test`": "Optika", "`query`": "", "`folder`": "", "`header`": ""}, {"`node_id`": 136, "`code`": 400, "`test`": "P\u0159\u00edroda", "`query`": "", "`folder`": "", "`header`": ""}, {"`node_id`": 137, "`code`": 500, "`test`": "\u010clov\u011bk", "`query`": "", "`folder`": "", "`header`": ""}, {"`node_id`": 138, "`code`": 600, "`test`": "V\u011bdy", "`query`": "konstanty", "`folder`": "", "`header`": ""}, {"`node_id`": 139, "`code`": 700, "`test`": "Technologie", "`query`": "", "`folder`": "", "`header`": ""}, {"`node_id`": 140, "`code`": 739, "`test`": "Orgon", "`query`": "", "`folder`": "", "`header`": ""}, {"`node_id`": 141, "`code`": 729, "`test`": "Hudba", "`query`": "", "`folder`": "", "`header`": ""}, {"`node_id`": 160, "`code`": 430, "`test`": "Slo\u017een\u00ed", "`query`": "", "`folder`": "CLIMAT", "`header`": ""}, {"`node_id`": 161, "`code`": 534, "`test`": "Filmy", "`query`": "", "`folder`": "MOV", "`header`": ""}, {"`node_id`": 163, "`code`": 738, "`test`": "Alternativn\u00ed", "`query`": "", "`folder`": "", "`header`": ""}, {"`node_id`": 165, "`code`": 533, "`test`": "Hudba", "`query`": "", "`folder`": "HDB", "`header`": ""}, {"`node_id`": 166, "`code`": 542, "`test`": "Pr\u00e1ce", "`query`": "", "`folder`": "", "`header`": ""}, {"`node_id`": 168, "`code`": 531, "`test`": "Knihy", "`query`": "knihy", "`folder`": "BOK", "`header`": ""}, {"`node_id`": 169, "`code`": 532, "`test`": "Obrazy", "`query`": "", "`folder`": "OBR", "`header`": ""}, {"`node_id`": 171, "`code`": 742, "`test`": "Database", "`query`": "", "`folder`": "DBS", "`header`": ""}, {"`node_id`": 173, "`code`": 411, "`test`": "Prvky", "`query`": "periodic", "`folder`": "PRV", "`header`": ""}, {"`node_id`": 174, "`code`": 412, "`test`": "Slou\u010deniny", "`query`": "latky", "`folder`": "LAT", "`header`": ""}, {"`node_id`": 175, "`code`": 751, "`test`": "Stavby", "`query`": "", "`folder`": "", "`header`": ""}, {"`node_id`": 178, "`code`": 641, "`test`": "Planety", "`query`": "", "`folder`": "", "`header`": ""}, {"`node_id`": 179, "`code`": 661, "`test`": "Element\u00e1rn\u00ed \u010d\u00e1stice", "`query`": "castice", "`folder`": "", "`header`": ""}, {"`node_id`": 180, "`code`": 611, "`test`": "\u010c\u00edsla", "`query`": "cisla", "`folder`": "NUM", "`header`": ""}, {"`node_id`": 181, "`code`": 612, "`test`": "\u010c\u00edslicov\u00e9 soustavy", "`query`": "soustavy", "`folder`": "", "`header`": ""}, {"`node_id`": 182, "`code`": 535, "`test`": "Jazyk", "`query`": "jazyky", "`folder`": "JAZ", "`header`": ""}, {"`node_id`": 184, "`code`": 536, "`test`": "Historie", "`query`": "histor", "`folder`": "HIS", "`header`": ""}, {"`node_id`": 186, "`code`": 525, "`test`": "Doprava", "`query`": "", "`folder`": "TRF", "`header`": ""}, {"`node_id`": 187, "`code`": 734, "`test`": "Slune\u010dn\u00ed", "`query`": "", "`folder`": "", "`header`": ""}, {"`node_id`": 188, "`code`": 733, "`test`": "V\u011btrn\u00e9", "`query`": "", "`folder`": "WND", "`header`": ""}, {"`node_id`": 189, "`code`": 731, "`test`": "Vodn\u00ed", "`query`": "", "`folder`": "WTR", "`header`": ""}, {"`node_id`": 190, "`code`": 614, "`test`": "Goniometrie", "`query`": "", "`folder`": "GON", "`header`": ""}, {"`node_id`": 191, "`code`": 631, "`test`": "Obecn\u00e1 chemie", "`query`": "", "`folder`": "", "`header`": ""}, {"`node_id`": 192, "`code`": 632, "`test`": "Anorganick\u00e1 chemie", "`query`": "", "`folder`": "ACH", "`header`": ""}, {"`node_id`": 193, "`code`": 735, "`test`": "Jadern\u00e1", "`query`": "", "`folder`": "", "`header`": ""}, {"`node_id`": 194, "`code`": 642, "`test`": "Slune\u010dn\u00ed soustava", "`query`": "planet", "`folder`": "", "`header`": ""}, {"`node_id`": 195, "`code`": 622, "`test`": "Vln\u011bn\u00ed", "`query`": "", "`folder`": "SIN", "`header`": ""}, {"`node_id`": 198, "`code`": 623, "`test`": "Elekt\u0159ina", "`query`": "", "`folder`": "ELK", "`header`": ""}, {"`node_id`": 199, "`code`": 624, "`test`": "Magnetismus", "`query`": "", "`folder`": "MAG", "`header`": ""}, {"`node_id`": 201, "`code`": 512, "`test`": "Suroviny", "`query`": "suroviny", "`folder`": "MEA", "`header`": ""}, {"`node_id`": 202, "`code`": 613, "`test`": "Algebra", "`query`": "", "`folder`": "", "`header`": ""}, {"`node_id`": 203, "`code`": 615, "`test`": "Geometrie", "`query`": "", "`folder`": "GEM", "`header`": ""}, {"`node_id`": 204, "`code`": 621, "`test`": "Mechanika t\u011bles", "`query`": "", "`folder`": "MCH", "`header`": ""}, {"`node_id`": 217, "`code`": 543, "`test`": "Socioekonomie", "`query`": "", "`folder`": "", "`header`": ""}, {"`node_id`": 220, "`code`": 544, "`test`": "Co-Workers", "`query`": "", "`folder`": "", "`header`": ""}, {"`node_id`": 236, "`code`": 723, "`test`": "Mechanika", "`query`": "", "`folder`": "", "`header`": ""}, {"`node_id`": 246, "`code`": 643, "`test`": "Cykly", "`query`": "", "`folder`": "", "`header`": ""}, {"`node_id`": 249, "`code`": 725, "`test`": "Laboratorn\u00ed", "`query`": "", "`folder`": "", "`header`": ""}, {"`node_id`": 250, "`code`": 726, "`test`": "Elektro", "`query`": "", "`folder`": "", "`header`": ""}, {"`node_id`": 253, "`code`": 722, "`test`": "Zahrada", "`query`": "", "`folder`": "", "`header`": ""}, {"`node_id`": 255, "`code`": 725, "`test`": "Transport", "`query`": "", "`folder`": "", "`header`": ""}, {"`node_id`": 256, "`code`": 545, "`test`": "St\u00e1tn\u00ed z\u0159\u00edzen\u00ed", "`query`": "", "`folder`": "", "`header`": ""}, {"`node_id`": 257, "`code`": 635, "`test`": "Fyzik\u00e1ln\u00ed chemie", "`query`": "", "`folder`": "FCH", "`header`": ""}, {"`node_id`": 258, "`code`": 553, "`test`": "Alchymie", "`query`": "", "`folder`": "ALC", "`header`": ""}, {"`node_id`": 265, "`code`": 721, "`test`": "Dom\u00e1c\u00ed", "`query`": "", "`folder`": "", "`header`": ""}, {"`node_id`": 267, "`code`": 552, "`test`": "Symbolika", "`query`": "symbol", "`folder`": "SMB", "`header`": ""}, {"`node_id`": 268, "`code`": 421, "`test`": "Archaea - Archbacterium", "`query`": "", "`folder`": "", "`header`": ""}, {"`node_id`": 272, "`code`": 524, "`test`": "Dom\u00e1c\u00ed cvi\u010den\u00ed", "`query`": "", "`folder`": "ERO", "`header`": ""}, {"`node_id`": 276, "`code`": 410, "`test`": "Mineraly", "`query`": "", "`folder`": "MINERAL", "`header`": ""}, {"`node_id`": 301, "`code`": 546, "`test`": "Finan\u010dnitv\u00ed", "`query`": "", "`folder`": "", "`header`": ""}, {"`node_id`": 309, "`code`": 549, "`test`": "Psychologie", "`query`": "", "`folder`": "", "`header`": ""}, {"`node_id`": 316, "`code`": 636, "`test`": "Aparatura", "`query`": "", "`folder`": "", "`header`": ""}, {"`node_id`": 317, "`code`": 637, "`test`": "Synt\u00e9za", "`query`": "", "`folder`": "", "`header`": ""}, {"`node_id`": 327, "`code`": 413, "`test`": "Nerosty", "`query`": "mineral", "`folder`": "MIN", "`header`": ""}, {"`node_id`": 328, "`code`": 431, "`test`": "Atmosf\u00e9ra", "`query`": "", "`folder`": "ATM", "`header`": ""}, {"`node_id`": 330, "`code`": 541, "`test`": "Identita", "`query`": "", "`folder`": "IDE", "`header`": ""}, {"`node_id`": 331, "`code`": 551, "`test`": "M\u00edsta", "`query`": "", "`folder`": "GEO", "`header`": ""}, {"`node_id`": 333, "`code`": 434, "`test`": "Cykly planet", "`query`": "", "`folder`": "", "`header`": ""}]